throttlestop/__init__.py
throttlestop/__main__.py
throttlestop/install.py
throttlestop/msr.py
throttlestop/tools.py
throttlestop-0.0.5.dist-info/entry_points.txt
throttlestop-0.0.5.dist-info/LICENSE.txt
throttlestop-0.0.5.dist-info/WHEEL
throttlestop-0.0.5.dist-info/METADATA
throttlestop-0.0.5.dist-info/RECORD
