Metadata-Version: 2.1
Name: throttlestop
Version: 0.0.5
Summary: Simple tool to manage throttling problems on Linux
License: MIT
Author: Angus Hollands
Author-email: goosey15@gmail.com
Requires-Python: >=3.6,<4.0
Classifier: License :: OSI Approved :: MIT License
Classifier: Programming Language :: Python :: 3
Classifier: Programming Language :: Python :: 3.6
Classifier: Programming Language :: Python :: 3.7
Classifier: Programming Language :: Python :: 3.8
Requires-Dist: numpy (>=1.16,<2.0)
Requires-Dist: plumbum (>=1.6,<2.0)
